bupt_session_py/__init__.py
bupt_session_py/api.py
bupt_session_py/exceptions.py
bupt_session_py/session.py
bupt_session-0.1.0.dist-info/LICENSE
bupt_session-0.1.0.dist-info/METADATA
bupt_session-0.1.0.dist-info/WHEEL
bupt_session-0.1.0.dist-info/top_level.txt
bupt_session-0.1.0.dist-info/zip-safe
bupt_session-0.1.0.dist-info/RECORD
