Metadata-Version: 2.1
Name: bupt-session
Version: 0.1.0
Summary: 北邮统一登录网关 API
Home-page: https://github.com/OpenBUPT/session
Author: RinChanNOWWW
Author-email: rinchannow@bupt.edu.cn
License: MIT
Keywords: python BUPT session login
Platform: UNKNOWN
Classifier: Development Status :: 5 - Production/Stable
Classifier: Intended Audience :: Developers
Classifier: Topic :: Software Development :: Libraries
Classifier: Programming Language :: Python :: 3
Requires-Dist: requests
Requires-Dist: typing-extensions
